svg_path_data/__init__.py
svg_path_data/float_string_conversion.py
svg_path_data/py.typed
svg_path_data/string_ops.py
svg_path_data/svg_data.py
svg_path_data-0.7.1.dist-info/WHEEL
svg_path_data-0.7.1.dist-info/METADATA
svg_path_data-0.7.1.dist-info/RECORD
