Metadata-Version: 2.4
Name: svg-path-data
Version: 0.7.1
Summary: Convert floats to svg-readable strings. Convert between svg path `d` strings and non-rational Bézier control points.
Author: Shay Hill
Author-email: Shay Hill <shay_public@hotmail.com>
License-Expression: MIT
Requires-Dist: paragraphs>=1.0.1
Requires-Python: >=3.10
